pymunin/__init__.py
pymunin/_version.py
PyMunin3-3.0.2.dist-info/LICENSE
PyMunin3-3.0.2.dist-info/METADATA
PyMunin3-3.0.2.dist-info/WHEEL
PyMunin3-3.0.2.dist-info/top_level.txt
PyMunin3-3.0.2.dist-info/RECORD
