Metadata-Version: 2.1
Name: PyMunin3
Version: 3.0.2
Summary: Package for developing Munin Multigraph Plugins
Home-page: https://aouyar.github.io/PyMunin
Author: Sandro
Author-email: devel@penguinpee.nl
License: GPLv3
Project-URL: Source Code, https://github.com/penguinpee/PyMunin3
Project-URL: Bug Tracker, https://github.com/penguinpee/PyMunin3/issues
Keywords: munin,monitoring
Classifier: Development Status :: 5 - Production/Stable
Classifier: Intended Audience :: Developers
Classifier: License :: OSI Approved :: GNU General Public License v3 (GPLv3)
Classifier: Operating System :: OS Independent
Classifier: Programming Language :: Python :: 3
Classifier: Topic :: Utilities
Classifier: Topic :: Software Development :: Libraries :: Python Modules
Classifier: Topic :: System :: Monitoring
Requires-Python: >=3.7
License-File: LICENSE
